pyepilepsy/__init__.py
pyepilepsy/metrics.py
pyEpilepsy-0.1.1.dist-info/LICENSE
pyEpilepsy-0.1.1.dist-info/METADATA
pyEpilepsy-0.1.1.dist-info/WHEEL
pyEpilepsy-0.1.1.dist-info/top_level.txt
pyEpilepsy-0.1.1.dist-info/RECORD
