Metadata-Version: 2.1
Name: pyEpilepsy
Version: 0.1.1
Summary: Epilepsy seizure forecasting package
Download-URL: https://github.com/etiennedemontalivet/pyEpilepsy.git
Maintainer: Etienne de Montalivet
Maintainer-email: etienne.demontalivet@protonmail.com
License: BSD (3-clause)
Platform: any
Classifier: Intended Audience :: Science/Research
Classifier: Intended Audience :: Developers
Classifier: License :: OSI Approved
Classifier: Programming Language :: Python
Classifier: Topic :: Software Development
Classifier: Topic :: Scientific/Engineering
Classifier: Operating System :: Microsoft :: Windows
Classifier: Operating System :: POSIX
Classifier: Operating System :: Unix
Classifier: Operating System :: MacOS
Classifier: Programming Language :: Python :: 3
Requires-Python: >=3.6
License-File: LICENSE
Requires-Dist: numpy
Requires-Dist: pandas
